LICENSE
README.md
setup.py
src/p5.aiogoldsrcrcon.egg-info/PKG-INFO
src/p5.aiogoldsrcrcon.egg-info/SOURCES.txt
src/p5.aiogoldsrcrcon.egg-info/dependency_links.txt
src/p5.aiogoldsrcrcon.egg-info/entry_points.txt
src/p5.aiogoldsrcrcon.egg-info/requires.txt
src/p5.aiogoldsrcrcon.egg-info/top_level.txt
src/p5/aiogoldsrcrcon/__init__.py
src/p5/aiogoldsrcrcon/__main__.py
src/p5/aiogoldsrcrcon/_entry_point.py
src/p5/aiogoldsrcrcon/connection.py
src/p5/aiogoldsrcrcon/_common/__init__.py
src/p5/aiogoldsrcrcon/_common/module_helpers/__init__.py
src/p5/aiogoldsrcrcon/_common/module_helpers/import_module.py
src/p5/aiogoldsrcrcon/_common/module_helpers/lazy_attributes.py