Metadata-Version: 2.1
Name: p5.aiogoldsrcrcon
Version: 0.0.3
Summary: asyncio rcon client for GoldSrc engine
Home-page: https://github.com/p5-vbnekit/p5-python3-aiogoldsrcrcon
Author: Nikita Pushchin
Author-email: vbnekit@gmail.com
License: UNKNOWN
Platform: UNKNOWN
License-File: LICENSE
